{"quota_remaining": 7537, "quota_max": 10000, "items": [{"owner": {"display_name": "Gerald Schneider", "user_id": 212107, "user_type": "registered", "reputation": 11482, "profile_image": "https://www.gravatar.com/avatar/1c1806ae596bd8311104f8b22dc0cb98?s=128&d=identicon&r=PG", "accept_rate": 100, "link": "http://stackoverflow.com/users/212107/gerald-schneider"}, "creation_date": 1360333908, "last_edit_date": 1477641601, "answer_id": 14774808, "is_accepted": false, "score": 8, "last_activity_date": 1477641601, "question_id": 14774700}, {"owner": {"display_name": "Will", "user_id": 145279, "user_type": "registered", "reputation": 10765, "profile_image": "https://i.stack.imgur.com/r9KgA.jpg?s=128&g=1", "accept_rate": 96, "link": "http://stackoverflow.com/users/145279/will"}, "creation_date": 1426567291, "answer_id": 29091401, "is_accepted": false, "score": 7, "last_activity_date": 1426567291, "question_id": 14774700}, {"owner": {"display_name": "Dave", "user_id": 2000726, "user_type": "registered", "reputation": 2706, "profile_image": "https://www.gravatar.com/avatar/bef3cbeb1ec9e35193fc2fad68f70e89?s=128&d=identicon&r=PG", "accept_rate": 71, "link": "http://stackoverflow.com/users/2000726/dave"}, "creation_date": 1360333961, "answer_id": 14774825, "is_accepted": false, "score": 1, "last_activity_date": 1360333961, "question_id": 14774700}], "has_more": false}