{"quota_remaining": 7087, "quota_max": 10000, "items": [{"owner": {"display_name": "Oleg Neumyvakin", "user_id": 1592008, "user_type": "registered", "reputation": 3554, "profile_image": "https://www.gravatar.com/avatar/4e208220f7cb95e6854adb653663736a?s=128&d=identicon&r=PG", "link": "http://stackoverflow.com/users/1592008/oleg-neumyvakin"}, "creation_date": 1477639631, "answer_id": 40300140, "is_accepted": true, "score": 0, "last_activity_date": 1477639631, "question_id": 40205052}], "has_more": false}