{"quota_remaining": 5365, "quota_max": 10000, "items": [{"owner": {"display_name": "guest271314", "user_id": 2801559, "user_type": "registered", "reputation": 47845, "profile_image": "https://www.gravatar.com/avatar/9538ef609067e6d6a842dfef189b77d2?s=128&d=identicon&r=PG", "accept_rate": 69, "link": "http://stackoverflow.com/users/2801559/guest271314"}, "creation_date": 1477610450, "last_edit_date": 1477626756, "answer_id": 40295682, "is_accepted": false, "score": 0, "last_activity_date": 1477626756, "question_id": 40295292}, {"owner": {"display_name": "Peter Leger", "user_id": 3589620, "user_type": "registered", "reputation": 2079, "profile_image": "https://i.stack.imgur.com/h0eFW.png?s=128&g=1", "accept_rate": 53, "link": "http://stackoverflow.com/users/3589620/peter-leger"}, "creation_date": 1477617997, "last_edit_date": 1477619431, "answer_id": 40296590, "is_accepted": false, "score": 0, "last_activity_date": 1477619431, "question_id": 40295292}, {"owner": {"display_name": "Javier Rey", "user_id": 3922265, "user_type": "registered", "reputation": 81, "profile_image": "https://i.stack.imgur.com/jH3is.jpg?s=128&g=1", "link": "http://stackoverflow.com/users/3922265/javier-rey"}, "creation_date": 1477615878, "last_edit_date": 1477616326, "answer_id": 40296341, "is_accepted": false, "score": 0, "last_activity_date": 1477616326, "question_id": 40295292}, {"owner": {"display_name": "Basim Hennawi", "user_id": 5433516, "user_type": "registered", "reputation": 26, "profile_image": "https://i.stack.imgur.com/NBSX6.jpg?s=128&g=1", "link": "http://stackoverflow.com/users/5433516/basim-hennawi"}, "creation_date": 1477609787, "last_edit_date": 1477613606, "answer_id": 40295571, "is_accepted": false, "score": 0, "last_activity_date": 1477613606, "question_id": 40295292}], "has_more": false}