{"quota_max": 10000, "has_more": false, "items": [{"badge_counts": {"bronze": 39, "silver": 10, "gold": 2}, "reputation_change_week": -10, "reputation_change_month": 26, "location": "Somewhere in earth..", "reputation_change_day": 0, "reputation_change_year": 1048, "user_type": "registered", "reputation": 2701, "last_access_date": 1477657454, "account_id": 4111146, "accept_rate": 88, "display_name": "Leo the lion", "link": "http://stackoverflow.com/users/3373905/leo-the-lion", "is_employee": false, "user_id": 3373905, "last_modified_date": 1477404442, "profile_image": "https://i.stack.imgur.com/9SVgr.jpg?s=128&g=1", "age": 28, "reputation_change_quarter": 26, "creation_date": 1393831080, "website_url": ""}], "quota_remaining": 5142}